icetk/__init__.py
icetk/ice_tokenizer.py
icetk/image_tokenizer.py
icetk/sentencepiece_model_pb2.py
icetk/text_tokenizer.py
icetk/utils.py
icetk/vqvae/__init__.py
icetk/vqvae/api.py
icetk/vqvae/enc_dec.py
icetk/vqvae/quantize.py
icetk/vqvae/vqvae_hierarchical.py
icetk-0.0.7.dist-info/METADATA
icetk-0.0.7.dist-info/WHEEL
icetk-0.0.7.dist-info/top_level.txt
icetk-0.0.7.dist-info/RECORD
