Metadata-Version: 2.1
Name: icetk
Version: 0.0.7
Summary: A unified tokenization tool for Images, Chinese and English.
Home-page: https://github.com/THUDM/icetk
Author: Wendi Zheng and Ming Ding
License: MIT license
Requires-Python: >=3.5
Requires-Dist: tqdm
Requires-Dist: requests
Requires-Dist: torchvision
Requires-Dist: sentencepiece
Requires-Dist: filelock
Requires-Dist: protobuf (<3.19)
